{
  "$schema": "https://json.schemastore.org/tsconfig",
  "display": "Default",
  "compilerOptions": {
    "declaration": true,
    "declarationMap": true,
    "emitDeclarationOnly": true,
    "allowSyntheticDefaultImports": true,
    "esModuleInterop": true,
    "target": "ESNext",
    "incremental": false,
    "isolatedModules": true,
    "module": "ESNext",
    "moduleDetection": "force",
    "moduleResolution": "Node",
    "noUncheckedIndexedAccess": true,
    "resolveJsonModule": true,
    "skipLibCheck": true,
    "strict": true,
  }
}
